[
    {
        "words": [
            {
                "Chinese": "春捲",
                "Simplified": "春卷",
                "English": "spring roll",
                "Yale": "chēun gyún",
                "Pinyin": "chūn juǎn",
                "resources": [
                    {
                        "name": "春捲",
                        "URL": "https://en.wiktionary.org/wiki/%E6%98%A5%E6%8D%B2"
                    },
                    {
                        "name": "春",
                        "URL": "https://en.wiktionary.org/wiki/%E6%98%A5"
                    },
                    {
                        "name": "捲",
                        "URL": "https://en.wiktionary.org/wiki/%E6%8D%B2"
                    }
                ]
            }
        ],
        "images": [
            {
                "image": "springrollsdimsumcafe",
                "place": "Dim Sum Cafe, Las Vegas, Nevada"
            }
        ],
        "description": "Cantonese [spring rolls](http://en.wikipedia.org/wiki/Spring_roll) are deep-fried with a thin crispy wrapper and filled with minced pork, bean sprouts, and other vegetables. Not to be confused with the deep-fried cabbage-filled burritos known as “egg rolls” in Chinese-American restaurants.\n\nIn mainland China, where Spring rolls originated (in fried and non-fried incarnations), they are traditionally eaten during the Spring (Chinese New Year) Festival, hence the name.\n\n**Characters**\n\n[春](https://en.wiktionary.org/wiki/%E6%98%A5) is *Spring*, and [捲](https://en.wiktionary.org/wiki/%E6%8D%B2) is *roll*, so, [春捲](https://en.wiktionary.org/wiki/%E6%98%A5%E6%8D%B2) is *Spring roll*.",
        "tags": [
            "春捲",
            "茶餐廳",
            "豬肉",
            "炸",
            "春",
            "捲",
            "點心"
        ],
        "resources": [
            {
                "name": "Dim Sum Guide",
                "URL": "https://dimsumguide.com/site/view/Spring-Roll"
            },
            {
                "name": "Hong Kong University",
                "URL": "https://learning.hku.hk/ccch9051/group-19/items/show/30"
            },
            {
                "name": "Panda Cheffy",
                "URL": "https://medium.com/@pandacheffy/spring-roll-春卷-40895f110047"
            },
            {
                "name": "Red House Spice",
                "URL": "https://redhousespice.com/chinese-spring-rolls/"
            },
            {
                "name": "Unfamiliar China",
                "URL": "https://www.unfamiliarchina.com/dim-sum/rolls/cantonese-spring-rolls"
            },
            {
                "name": "Wikipedia",
                "URL": "http://en.wikipedia.org/wiki/Spring_roll"
            },
            {
                "name": "The Woks of Life",
                "URL": "https://thewoksoflife.com/2015/09/homemade-spring-rolls/"
            }
        ]
    },
    {
        "words": [
            {
                "Chinese": "素春捲",
                "Simplified": "素春卷",
                "English": "vegetable spring roll",
                "Yale": "sou chēun gyún",
                "Pinyin": "sù chūn juǎn",
                "resources": [
                    {
                        "name": "素",
                        "URL": "https://en.wiktionary.org/wiki/%E7%B4%A0"
                    },
                    {
                        "name": "春捲",
                        "URL": "https://en.wiktionary.org/wiki/%E6%98%A5%E6%8D%B2"
                    },
                    {
                        "name": "春",
                        "URL": "https://en.wiktionary.org/wiki/%E6%98%A5"
                    },
                    {
                        "name": "捲",
                        "URL": "https://en.wiktionary.org/wiki/%E6%8D%B2"
                    }
                ]
            }
        ],
        "images": [
            {
                "image": "vegetablespringrollsnorthsidecafe",
                "place": "Northside Cafe, Las Vegas, Nevada"
            }
        ],
        "description": "[Spring rolls](http://en.wikipedia.org/wiki/Spring_roll) with no meat, just vegetables.\n\n**Characters**\n\nThe first character [素](https://en.wiktionary.org/wiki/%E7%B4%A0) is *vegetable*, [春](https://en.wiktionary.org/wiki/%E6%98%A5) is *Spring*, and [捲](https://en.wiktionary.org/wiki/%E6%8D%B2) is *roll*, so 素春捲 is *vegetable Spring roll*.",
        "tags": [
            "茶餐廳",
            "春捲",
            "素",
            "炸",
            "春",
            "捲",
            "點心"
        ],
        "resources": [
            {
                "name": "Dimsumptuous",
                "URL": "http://www.dimsumptuous.com/2013/04/vegetable-spring-rolls.html"
            },
            {
                "name": "Made with Lau",
                "URL": "https://www.madewithlau.com/recipes/egg-rolls"
            },
            {
                "name": "Thirsty for Tea",
                "URL": "http://www.thirstyfortea.com/recipes/dim-sum-recipe-veggie-egg-rolls/"
            },
            {
                "name": "Viet World Kitchen",
                "URL": "https://eggwansfoododyssey.com/2010/04/19/vegetarian-spring-rolls/"
            }
        ]
    },
    {
        "words": [
            {
                "Chinese": "蛋白蝦春捲",
                "Simplified": "蛋白虾春卷",
                "English": "egg white and shrimp spring roll",
                "Yale": "dáan baahk hā chēun gyún",
                "Pinyin": "dàn bái xiā chūn juǎn",
                "resources": [
                    {
                        "name": "蛋白",
                        "URL": "https://en.wiktionary.org/wiki/%E8%9B%8B%E7%99%BD"
                    },
                    {
                        "name": "蛋",
                        "URL": "https://en.wiktionary.org/wiki/%E8%9B%8B"
                    },
                    {
                        "name": "白",
                        "URL": "https://en.wiktionary.org/wiki/%E7%99%BD"
                    },
                    {
                        "name": "蝦",
                        "URL": "https://en.wiktionary.org/wiki/%E8%9D%A6"
                    },
                    {
                        "name": "春捲",
                        "URL": "https://en.wiktionary.org/wiki/%E6%98%A5%E6%8D%B2"
                    },
                    {
                        "name": "春",
                        "URL": "https://en.wiktionary.org/wiki/%E6%98%A5"
                    },
                    {
                        "name": "捲",
                        "URL": "https://en.wiktionary.org/wiki/%E6%8D%B2"
                    }
                ]
            }
        ],
        "images": [
            {
                "image": "eggwhiteshrimpspringrolltimhowan",
                "place": "Tim Ho Wan, Las Vegas, Nevada"
            }
        ],
        "description": "[Spring rolls](http://en.wikipedia.org/wiki/Spring_roll) containing shrimp and egg white.\n\n*Characters**\n\nThe first character 蛋 is “egg“, the second character 白 is “white,” and the third character 蝦 is “shrimp,” so it's “egg white shrimp Spring roll.”",
        "tags": [
            "春捲",
            "蛋白",
            "蝦",
            "炸",
            "春",
            "捲",
            "海鮮",
            "點心"
        ],
        "resources": [
            {
                "name": "Tim Ho Wan",
                "URL": "http://timhowanusa.com/menus/deep-fried-spring-roll-with-egg-white-and-shrimp/"
            }
        ]
    },
    {
        "words": [
            {
                "Chinese": "炸蝦捲",
                "Simplified": "炸虾卷",
                "English": "fried shrimp roll",
                "Yale": "ja hā gyún",
                "Pinyin": "zhà xiā juǎn",
                "resources": [
                    {
                        "name": "炸",
                        "URL": "https://en.wiktionary.org/wiki/%E7%82%B8"
                    },
                    {
                        "name": "蝦",
                        "URL": "https://en.wiktionary.org/wiki/%E8%9D%A6"
                    },
                    {
                        "name": "捲",
                        "URL": "https://en.wiktionary.org/wiki/%E6%8D%B2"
                    }
                ]
            }
        ],
        "images": [
            {
                "image": "shrimprollsyumcha",
                "place": "Yum Cha, Las Vegas, Nevada"
            }
        ],
        "description": "[Spring rolls](http://en.wikipedia.org/wiki/Spring_roll) with just shrimp inside.\n\n*Characters**\n\nThe first character 炸 is the word for “deep-fried,” the second character 蝦 is “shrimp,” and the third character 捲 is the word for “roll,” so, “deep-fried shrimp roll.”",
        "tags": [
            "春捲",
            "炸",
            "蝦",
            "捲",
            "海鮮",
            "點心"
        ],
        "resources": [
            {
                "name": "Simple Comfort Food",
                "URL": "http://www.simplecomfortfood.com/2012/06/05/shrimp-egg-rolls/"
            }
        ]
    },
    {
        "words": [
            {
                "Chinese": "炸海菜捲",
                "Simplified": "炸海菜卷",
                "English": "deep-fried seaweed roll",
                "Yale": "ja hói choi gyún",
                "Pinyin": "zhà hǎi cài juǎn",
                "resources": [
                    {
                        "name": "炸",
                        "URL": "https://en.wiktionary.org/wiki/%E7%82%B8"
                    },
                    {
                        "name": "海菜",
                        "URL": "https://en.wiktionary.org/wiki/%E6%B5%B7%E8%8F%9C"
                    },
                    {
                        "name": "海",
                        "URL": "https://en.wiktionary.org/wiki/%E6%B5%B7"
                    },
                    {
                        "name": "菜",
                        "URL": "https://en.wiktionary.org/wiki/%E8%8F%9C"
                    },
                    {
                        "name": "捲",
                        "URL": "https://en.wiktionary.org/wiki/%E6%8D%B2"
                    }
                ]
            }
        ],
        "images": [
            {
                "image": "seaweedrollchinarepublic",
                "place": "China Republic, Rancho Cucamonga, California"
            }
        ],
        "description": "Deep-fried rolls with a seaweed wrapper, typically with shrimp inside.\n\n*Characters**\n\n[炸](https://en.wiktionary.org/wiki/%E7%82%B8) is *deep-fried*, 海菜 means “seaweed“, and the final character 捲 is the word for “roll,” so, “deep-fried seaweed roll.”",
        "tags": [
            "海菜",
            "炸",
            "蝦",
            "捲",
            "海鮮",
            "點心"
        ],
        "resources": [
            {
                "name": "Hawaii Magazine",
                "URL": "https://www.hawaiimagazine.com/content/recipe-jade-dynastys-fried-seaweed-nori-roll"
            }
        ]
    }
]
