{
    "name": "Guam",
    "places": [
        {
            "name": "Jerry Kitchen",
            "links": [
                {
                    "name": "Visit Guam",
                    "URL": "https://www.visitguam.com/listing/jerry-kitchen/5115/"
                }
            ],
            "lat": 13.488050,
            "lon": 144.784973,
            "city": "Tamuning",
            "address": "541 S Marine Corps Dr Bldg 102 & 103 Tamuning, Guam 96913"
        },
        {
            "name": "Kar Kar Restaurant",
            "links": [
                {
                    "name": "Stripes Guam",
                    "URL": "https://guam.stripes.com/food-drink/guam-diner-bytes-kar-kar-restaurant"
                }
            ],
            "lat": 13.490510,
            "lon": 144.783905,
            "city": "Tamuning",
            "address": "194 Chalan San Antonio Tamuning, Guam 96913 Guam"
        }
    ]
}
