{
    "name": "Minnesota",
    "places": [
        
        {
            "title": "A & L Chinese Restaurant",
            "links":
            [
            {
                "name":"Yelp",
                "URL":"https://www.yelp.com/biz/a-and-l-chinese-restaurant-inver-grove-heights"
                }
            ],
            "lat": 44.864720,
            "lon": -93.041750,
            "city": "Inver Grove Heights",
            "address": "5800 Cahill Ave Inver Grove Heights, MN 55076"
        },
        
        {
            "title": "Mandarin Kitchen",
            "links":
            [
                {
                    "name":"site",
            "URL":"http://mandarin-kitchen-bloomington.sites.tablehero.com"
            },
                {
                    "name":"Yelp",
                    "URL":"https://www.yelp.com/biz/mandarin-kitchen-minneapolis-2"
            }
            ],
            "lat": 44.831670,
            "lon": -93.288580,
            "city": "Minneapolis",
            "address": "8766 Lyndale Ave S Minneapolis, MN 55420"
        },
        {
            "title": "JUN",
            "links":
            [
                {
                    "name":"site",
            "URL":"http://junnorthloop.com"
            },
                {
                    "name":"Yelp",
                    "URL":"https://www.yelp.com/biz/jun-minneapolis"
            }
            ],
            "lat": 44.988700,
            "lon": -93.277740,
            "city": "Minneapolis",
            "address": "730 N Washington Ave Minneapolis, MN 55401"
        },
        {
            "title": "Pagoda",
            "links":
            [
                {
                    "name":"site",
            "URL":"http://pagodadinkytown.com"
            },
                {
                    "name":"Yelp",
                    "URL":"https://www.yelp.com/biz/pagoda-minneapolis-5"
            }
            ],
            "lat": 44.980440,
            "lon": -93.234640,
            "city": "Minneapolis",
            "address": "1417 4th St SE Minneapolis, MN 55414"
        },


        {
            "title": "Yangtze",
            "links":
            [
                {
                    "name":"site",
            "URL":"http://www.yangtze.uss"
            },
                {
                    "name":"Yelp",
                    "URL":"https://www.yelp.com/biz/yangtze-st-louis-park"
            }
            ],
            "lat": 44.969510,
            "lon": -93.351480,
            "city": "Saint Louis Park",
            "address": "5625 Wayzata Blvd St. Louis Park, MN 55416"
        },
        
        {
            "title": "Tapestry",
            "links":
            [
                {
                    "name":"site",
            "URL":"https://www.tapestryrestaurant.org"
            },
                {
                    "name":"Yelp",
                    "URL":"https://www.yelp.com/biz/tapestry-saint-paul-2"
            }
            ],
            "lat": 44.955510,
            "lon": -93.116610,
            "city": "Saint Paul",
            "address": "394 University Ave Saint Paul, MN 55103"
        }

        
     
        
 ]
    
}
